{"Orders": {"0": {"Account": "Cash", "From": "Feb\n2021", "To": "Nov\n2025", "Day": "3.", "Purpose": "Eat & Drink", "Amount": 172.59, "MonthListed": false}, "1": {"Account": "DKB", "From": "Mar\n2021", "To": "Feb\n2024", "Day": "3.", "Purpose": "Culture", "Amount": -192.39, "MonthListed": false}, "2": {"Account": "DKB", "From": "Apr\n2021", "To": "Sep\n2022", "Day": "2.", "Purpose": "Eat & Drink", "Amount": 184.89, "MonthListed": true}, "3": {"Account": "Cash", "From": "Jul\n2021", "To": "Sep\n2025", "Day": "4.", "Purpose": "M\u00f6bel", "Amount": 119.12, "MonthListed": false}, "4": {"Account": "ING", "From": "Jan\n2021", "To": "Apr\n2023", "Day": "3.", "Purpose": "Restaurant", "Amount": -77.12, "MonthListed": false}, "5": {"Account": "ING", "From": "Mar\n2021", "To": "Sep\n2025", "Day": "2.", "Purpose": "Schuhe", "Amount": -189.83, "MonthListed": true}, "6": {"Account": "DKB", "From": "Apr\n2021", "To": "Sep\n2022", "Day": "2.", "Purpose": "Flug", "Amount": 140.89, "MonthListed": true}, "7": {"Account": "Cash", "From": "Mai\n2021", "To": "Feb\n2024", "Day": "1.", "Purpose": "Bier", "Amount": 173.01, "MonthListed": true}, "8": {"Account": "ING", "From": "Apr\n2021", "To": "Jul\n2025", "Day": "1.", "Purpose": "Eis", "Amount": -186.51, "MonthListed": true}, "9": {"Account": "ING", "From": "Mai\n2021", "To": "Dez\n2025", "Day": "2.", "Purpose": "Bier", "Amount": -97.75, "MonthListed": true}}, "Reset date": "2021-06-02"}